odoo/addons/invader_payment_manual/README.rst
odoo/addons/invader_payment_manual/__init__.py
odoo/addons/invader_payment_manual/__manifest__.py
odoo/addons/invader_payment_manual/data/payment_acquirer_data.xml
odoo/addons/invader_payment_manual/i18n/invader_payment_manual.pot
odoo/addons/invader_payment_manual/readme/CONTRIBUTORS.rst
odoo/addons/invader_payment_manual/readme/DESCRIPTION.rst
odoo/addons/invader_payment_manual/services/__init__.py
odoo/addons/invader_payment_manual/services/payment_manual.py
odoo/addons/invader_payment_manual/static/description/index.html
odoo13_addon_invader_payment_manual-13.0.1.0.1.dev4.dist-info/METADATA
odoo13_addon_invader_payment_manual-13.0.1.0.1.dev4.dist-info/WHEEL
odoo13_addon_invader_payment_manual-13.0.1.0.1.dev4.dist-info/top_level.txt
odoo13_addon_invader_payment_manual-13.0.1.0.1.dev4.dist-info/RECORD
