Metadata-Version: 2.1
Name: odoo13-addon-invader_payment_manual
Version: 13.0.1.0.1.dev4
Summary: REST Services for manual payment like bank transfer, check ... (base module)
Home-page: https://github.com/shopinvader/odoo-shopinvader-payment
Author: ACSONE SA/NV
License: AGPL-3
Classifier: Programming Language :: Python
Classifier: Framework :: Odoo
Classifier: Framework :: Odoo :: 13.0
Classifier: License :: OSI Approved :: GNU Affero General Public License v3
Requires-Python: >=3.5
Requires-Dist: cerberus
Requires-Dist: odoo13-addon-base-rest
Requires-Dist: odoo13-addon-invader-payment
Requires-Dist: odoo <13.1dev,>=13.0a
